kei_agent/__init__.py
kei_agent/a2a.py
kei_agent/agent_skeleton.py
kei_agent/alerting.py
kei_agent/capabilities.py
kei_agent/cli.py
kei_agent/client.py
kei_agent/config_api.py
kei_agent/config_manager.py
kei_agent/dashboard_generators.py
kei_agent/discovery.py
kei_agent/enterprise_logging.py
kei_agent/error_aggregation.py
kei_agent/exceptions.py
kei_agent/health_checks.py
kei_agent/input_sanitizer.py
kei_agent/input_validation.py
kei_agent/kei_agent.py
kei_agent/metrics.py
kei_agent/metrics_server.py
kei_agent/models.py
kei_agent/protocol_clients.py
kei_agent/protocol_selector.py
kei_agent/protocol_types.py
kei_agent/py.typed
kei_agent/retry.py
kei_agent/secrets_manager.py
kei_agent/security_manager.py
kei_agent/tracing.py
kei_agent/unified_client.py
kei_agent/utils.py
kei_agent/validate_setup.py
kei_agent/validation_models.py
kei_agent/caching/__init__.py
kei_agent/caching/cache_framework.py
kei_agent/caching/cache_manager.py
kei_agent/caching/memory_cache.py
kei_agent/caching/multi_level_cache.py
kei_agent/caching/persistent_cache.py
kei_agent/caching/redis_cache.py
kei_agent/caching/specialized_caches.py
kei_agent_py_sdk-0.1.0b6.dist-info/licenses/LICENSE
kei_agent_py_sdk-0.1.0b6.dist-info/METADATA
kei_agent_py_sdk-0.1.0b6.dist-info/WHEEL
kei_agent_py_sdk-0.1.0b6.dist-info/entry_points.txt
kei_agent_py_sdk-0.1.0b6.dist-info/top_level.txt
kei_agent_py_sdk-0.1.0b6.dist-info/RECORD
