Metadata-Version: 2.4
Name: kei_agent_py_sdk
Version: 0.1.0b6
Summary: Enterprise-Grade Python SDK for Keiko-Personal-Assistant Platform with Multi-Protocol Support and Comprehensive Documentation
Author-email: Oliver Scharkowski <o.scharkowski@oscharko.de>
Maintainer-email: Oliver Scharkowski <o.scharkowski@oscharko.de>
License: MIT
Project-URL: Homepage, https://oscharko.de
Project-URL: Documentation, https://oscharko-dev.github.io/kei-agent-py-sdk/
Project-URL: Repository, https://github.com/oscharko-dev/kei-agent-py-sdk
Project-URL: Bug Tracker, https://github.com/oscharko-dev/kei-agent-py-sdk/issues
Project-URL: Changelog, https://github.com/oscharko-dev/kei-agent-py-sdk/blob/main/CHANGELOG.md
Keywords: ai,agent,multi-agent,framework,rpc,stream,bus,mcp,enterprise,async,distributed,tracing,monitoring,resilience
Classifier: Development Status :: 4 - Beta
Classifier: Intended Audience :: Developers
Classifier: Intended Audience :: Information Technology
Classifier: Intended Audience :: Science/Research
Classifier: Topic :: Software Development :: Libraries :: Python Modules
Classifier: Topic :: Scientific/Engineering :: Artificial Intelligence
Classifier: Topic :: System :: Distributed Computing
Classifier: Topic :: Internet :: WWW/HTTP :: HTTP Servers
Classifier: Programming Language :: Python :: 3
Classifier: Programming Language :: Python :: 3.8
Classifier: Programming Language :: Python :: 3.9
Classifier: Programming Language :: Python :: 3.10
Classifier: Programming Language :: Python :: 3.11
Classifier: Programming Language :: Python :: 3.12
Classifier: Operating System :: OS Independent
Classifier: Framework :: AsyncIO
Classifier: Typing :: Typed
Requires-Python: >=3.8
License-File: LICENSE
Requires-Dist: aiohttp<4.0.0,>=3.9.0
Requires-Dist: httpx<1.0.0,>=0.24.0
Requires-Dist: websockets<12.0.0,>=11.0.0
Requires-Dist: pydantic<3.0.0,>=2.0.0
Requires-Dist: typing-extensions>=4.0.0
Requires-Dist: importlib-metadata>=4.0.0; python_version < "3.8"
Requires-Dist: opentelemetry-api<2.0.0,>=1.20.0
Requires-Dist: opentelemetry-sdk<2.0.0,>=1.20.0
Requires-Dist: opentelemetry-exporter-jaeger<2.0.0,>=1.20.0
Requires-Dist: opentelemetry-exporter-zipkin-json<2.0.0,>=1.20.0
Requires-Dist: opentelemetry-propagator-b3<2.0.0,>=1.20.0
Requires-Dist: tenacity<9.0.0,>=8.2.0
Requires-Dist: msgpack<2.0.0,>=1.0.0
Requires-Dist: pyyaml<7.0.0,>=6.0.0
Requires-Dist: watchdog<5.0.0,>=2.1.0
Requires-Dist: packaging>=21.0
Requires-Dist: python-dateutil>=2.8.0
Requires-Dist: psutil<8.0.0,>=5.9.0
Requires-Dist: structlog<26.0.0,>=23.1.0
Requires-Dist: click<9.0,>=8.0
Requires-Dist: rich<14.0,>=13.0
Provides-Extra: security
Requires-Dist: authlib<2.0.0,>=1.2.0; extra == "security"
Requires-Dist: cryptography<42.0.0,>=41.0.0; extra == "security"
Requires-Dist: pyopenssl<26.0.0,>=23.0.0; extra == "security"
Provides-Extra: dev
Requires-Dist: pytest<8.0.0,>=7.4.0; extra == "dev"
Requires-Dist: pytest-asyncio<1.0.0,>=0.21.0; extra == "dev"
Requires-Dist: pytest-mock<4.0.0,>=3.11.0; extra == "dev"
Requires-Dist: pytest-benchmark<6.0.0,>=4.0.0; extra == "dev"
Requires-Dist: pytest-cov<5.0.0,>=4.1.0; extra == "dev"
Requires-Dist: coverage<8.0.0,>=7.3.0; extra == "dev"
Requires-Dist: ruff<1.0.0,>=0.1.0; extra == "dev"
Requires-Dist: mypy<2.0.0,>=1.5.0; extra == "dev"
Requires-Dist: lxml<7.0.0,>=4.9.0; extra == "dev"
Requires-Dist: bandit<2.0.0,>=1.7.0; extra == "dev"
Requires-Dist: pre-commit<4.0.0,>=3.4.0; extra == "dev"
Requires-Dist: twine<5.0.0,>=4.0.0; extra == "dev"
Requires-Dist: build<2.0.0,>=0.10.0; extra == "dev"
Requires-Dist: jsonschema<5.0.0,>=4.17.0; extra == "dev"
Requires-Dist: safety<4.0.0,>=3.0.0; extra == "dev"
Requires-Dist: pip-audit<3.0.0,>=2.6.0; extra == "dev"
Requires-Dist: cyclonedx-bom<8.0.0,>=4.0.0; extra == "dev"
Requires-Dist: pip-tools<8.0.0,>=7.0.0; extra == "dev"
Provides-Extra: docs
Requires-Dist: mkdocs<2.0.0,>=1.5.0; extra == "docs"
Requires-Dist: mkdocs-material<10.0.0,>=9.4.0; extra == "docs"
Requires-Dist: mkdocs-autorefs<2.0.0,>=0.5.0; extra == "docs"
Requires-Dist: mkdocstrings[python]<1.0.0,>=0.23.0; extra == "docs"
Requires-Dist: mkdocs-mermaid2-plugin<2.0.0,>=1.1.0; extra == "docs"
Requires-Dist: mkdocs-git-revision-date-localized-plugin<2.0.0,>=1.2.0; extra == "docs"
Requires-Dist: mkdocs-minify-plugin<1.0.0,>=0.7.0; extra == "docs"
Requires-Dist: mkdocs-redirects<2.0.0,>=1.2.0; extra == "docs"
Provides-Extra: all
Requires-Dist: kei_agent_py_sdk[dev,docs,security]; extra == "all"
Dynamic: license-file
